celleditpy/__init___.py
celleditpy/main.py
celleditpy-0.1.7.dist-info/METADATA
celleditpy-0.1.7.dist-info/WHEEL
celleditpy-0.1.7.dist-info/entry_points.txt
celleditpy-0.1.7.dist-info/top_level.txt
celleditpy-0.1.7.dist-info/RECORD
