Metadata-Version: 2.4
Name: CelleditPy
Version: 0.1.7
Summary: A GUI tool to set and adjust unit cell parameters for molecular structures.
Author-email: HiroYokoyama <titech.yoko.hiro@gmail.com>
License: Apache-2.0
Project-URL: Homepage, https://github.com/HiroYokoyama/crystal-cell-settler
Project-URL: Repository, https://github.com/HiroYokoyama/crystal-cell-settler
Classifier: Programming Language :: Python :: 3
Classifier: Operating System :: OS Independent
Classifier: Intended Audience :: Science/Research
Classifier: Topic :: Scientific/Engineering :: Chemistry
Classifier: Topic :: Scientific/Engineering :: Visualization
Classifier: Environment :: X11 Applications :: Qt
Requires-Python: >=3.8
Requires-Dist: numpy
Requires-Dist: pyvista
Requires-Dist: PyQt6
Requires-Dist: pyvistaqt
Requires-Dist: ase
Requires-Dist: scipy
